subsdata/__init__.py
subsdata/sdp.py
subsdata-0.1.2.dist-info/LICENSE
subsdata-0.1.2.dist-info/METADATA
subsdata-0.1.2.dist-info/WHEEL
subsdata-0.1.2.dist-info/top_level.txt
subsdata-0.1.2.dist-info/RECORD
