Metadata-Version: 2.1
Name: subsdata
Version: 0.1.2
Summary: SDP: Subscription Data Protocol
Home-page: https://gitlab.com/miguel.alarcos/subsdata
Author: Miguel Ángel Alarcos Torrecillas
Author-email: miguel.alarcos@gmail.com
License: UNKNOWN
Platform: UNKNOWN
Classifier: Programming Language :: Python :: 3
Classifier: License :: OSI Approved :: MIT License
Classifier: Operating System :: OS Independent
Requires-Dist: PyJWT (>=1.6.4)
Requires-Dist: rethinkdb (>=2.3.0.post6)
